cn_sort/__init__.py
cn_sort/decorator.py
cn_sort/process_cn_word.py
cn_sort/res/all_word.csv
cn_sort/res/logging.conf
cn_sort-0.6.2.dist-info/METADATA
cn_sort-0.6.2.dist-info/WHEEL
cn_sort-0.6.2.dist-info/top_level.txt
cn_sort-0.6.2.dist-info/RECORD
