Metadata-Version: 2.1
Name: cn-sort
Version: 0.6.2
Summary: 按拼音和笔顺快速排序大量简体中文词组（支持百万数量级）。
Home-page: https://github.com/bmxbmx3/cn_sort/tree/master
Author: bmxbmx3
Author-email: 982766639@qq.com
License: MIT
Download-URL: https://pypi.org/project/cn-sort/#files
Keywords: njupt chinese word sort pronounce bihua 排序 中文 拼音 笔画 笔顺 词 汉字
Platform: UNKNOWN
Classifier: Development Status :: 4 - Beta
Classifier: Intended Audience :: Developers
Classifier: Topic :: Software Development :: Build Tools
Classifier: License :: OSI Approved :: MIT License
Classifier: Programming Language :: Python :: 3.6
Classifier: Programming Language :: Python :: 3.7
Requires-Python: >=3.6
Requires-Dist: pypinyin
Requires-Dist: jieba
